shapes/__init__.py
shapes/dataset.py
shapes/utils.py
shapeset-0.1.1.dist-info/licenses/LICENSE
shapeset-0.1.1.dist-info/METADATA
shapeset-0.1.1.dist-info/WHEEL
shapeset-0.1.1.dist-info/top_level.txt
shapeset-0.1.1.dist-info/RECORD
