Metadata-Version: 2.4
Name: ShapeSet
Version: 0.1.1
Summary: This package helps generate datasets of simple shapes like squares, circles, triangles, etc. for computer vision tasks.
Author-email: Manideep Reddy Enugala <enugalamanideepreddy99@gmail.com>
License: MIT License
Classifier: Programming Language :: Python :: 3
Classifier: License :: OSI Approved :: MIT License
Classifier: Operating System :: OS Independent
Requires-Python: >=3.9
License-File: LICENSE
Requires-Dist: numpy
Requires-Dist: opencv-python
Requires-Dist: tqdm
Requires-Dist: pytest
Requires-Dist: pillow
Dynamic: license-file
